requestsexceptions/__init__.py
requestsexceptions-1.3.0.dist-info/DESCRIPTION.rst
requestsexceptions-1.3.0.dist-info/METADATA
requestsexceptions-1.3.0.dist-info/RECORD
requestsexceptions-1.3.0.dist-info/WHEEL
requestsexceptions-1.3.0.dist-info/metadata.json
requestsexceptions-1.3.0.dist-info/pbr.json
requestsexceptions-1.3.0.dist-info/top_level.txt
